nzpermits/__init__.py
nzpermits/gjson.py
nzpermits/iris.py
nzpermits/models.py
nzpermits/utils.py
nzpermits/datasets/__init__.py
nzpermits/datasets/es_stream_depletion_ratios.csv
nzpermits/tests/permit_schema.json
nzpermits/tests/test_iris.py
nz_rma_permits-0.1.12.dist-info/METADATA
nz_rma_permits-0.1.12.dist-info/WHEEL
nz_rma_permits-0.1.12.dist-info/licenses/LICENSE
nz_rma_permits-0.1.12.dist-info/RECORD
