Metadata-Version: 2.4
Name: nz-rma-permits
Version: 0.1.12
Summary: Functions to process NZ RMA permit data
Project-URL: Homepage, https://github.com/mullenkamp/nz-rma-permits
Author-email: Mike Kittridge <mullenkamp1@gmail.com>
License-Expression: Apache-2.0
License-File: LICENSE
Keywords: nz,permits,rma
Classifier: Development Status :: 3 - Alpha
Classifier: Intended Audience :: Developers
Classifier: License :: OSI Approved :: Apache Software License
Classifier: Programming Language :: Python :: 2
Classifier: Programming Language :: Python :: 2.7
Classifier: Programming Language :: Python :: 3
Classifier: Programming Language :: Python :: 3.4
Classifier: Programming Language :: Python :: 3.5
Classifier: Programming Language :: Python :: 3.6
Classifier: Topic :: Software Development :: Build Tools
Requires-Python: >=3.10
Requires-Dist: msgspec
Requires-Dist: shapely
